/// JVM opcode constants shared across analysis rules.
pub(crate) const NOP: u8 = 0x00;
pub(crate) const ACONST_NULL: u8 = 0x01;
pub(crate) const GOTO: u8 = 0xa7;
pub(crate) const JSR: u8 = 0xa8;
pub(crate) const GOTO_W: u8 = 0xc8;
pub(crate) const JSR_W: u8 = 0xc9;
pub(crate) const IRETURN: u8 = 0xac;
pub(crate) const LRETURN: u8 = 0xad;
pub(crate) const FRETURN: u8 = 0xae;
pub(crate) const DRETURN: u8 = 0xaf;
pub(crate) const ARETURN: u8 = 0xb0;
pub(crate) const RETURN: u8 = 0xb1;
pub(crate) const ATHROW: u8 = 0xbf;
pub(crate) const ALOAD: u8 = 0x19;
pub(crate) const ALOAD_0: u8 = 0x2a;
pub(crate) const ALOAD_1: u8 = 0x2b;
pub(crate) const ALOAD_2: u8 = 0x2c;
pub(crate) const ALOAD_3: u8 = 0x2d;
pub(crate) const ASTORE: u8 = 0x3a;
pub(crate) const ASTORE_0: u8 = 0x4b;
pub(crate) const ASTORE_1: u8 = 0x4c;
pub(crate) const ASTORE_2: u8 = 0x4d;
pub(crate) const ASTORE_3: u8 = 0x4e;
pub(crate) const POP: u8 = 0x57;
pub(crate) const DUP: u8 = 0x59;
pub(crate) const NEW: u8 = 0xbb;
pub(crate) const IFNULL: u8 = 0xc6;
pub(crate) const IFNONNULL: u8 = 0xc7;
pub(crate) const INVOKEVIRTUAL: u8 = 0xb6;
pub(crate) const INVOKESPECIAL: u8 = 0xb7;
pub(crate) const INVOKESTATIC: u8 = 0xb8;
pub(crate) const INVOKEINTERFACE: u8 = 0xb9;
pub(crate) const INVOKEDYNAMIC: u8 = 0xba;
pub(crate) const LDC: u8 = 0x12;
pub(crate) const LDC_W: u8 = 0x13;
pub(crate) const LDC2_W: u8 = 0x14;
