/// JVM opcode constants shared across analysis rules.
pub(crate) const NOP: u8 = 0x00;
pub(crate) const ACONST_NULL: u8 = 0x01;
pub(crate) const ICONST_M1: u8 = 0x02;
pub(crate) const ICONST_0: u8 = 0x03;
pub(crate) const ICONST_1: u8 = 0x04;
pub(crate) const ICONST_2: u8 = 0x05;
pub(crate) const ICONST_3: u8 = 0x06;
pub(crate) const ICONST_4: u8 = 0x07;
pub(crate) const ICONST_5: u8 = 0x08;
pub(crate) const LCONST_0: u8 = 0x09;
pub(crate) const LCONST_1: u8 = 0x0a;
pub(crate) const FCONST_0: u8 = 0x0b;
pub(crate) const FCONST_1: u8 = 0x0c;
pub(crate) const FCONST_2: u8 = 0x0d;
pub(crate) const DCONST_0: u8 = 0x0e;
pub(crate) const DCONST_1: u8 = 0x0f;
pub(crate) const BIPUSH: u8 = 0x10;
pub(crate) const SIPUSH: u8 = 0x11;
pub(crate) const ILOAD: u8 = 0x15;
pub(crate) const LLOAD: u8 = 0x16;
pub(crate) const FLOAD: u8 = 0x17;
pub(crate) const DLOAD: u8 = 0x18;
pub(crate) const ILOAD_0: u8 = 0x1a;
pub(crate) const ILOAD_1: u8 = 0x1b;
pub(crate) const ILOAD_2: u8 = 0x1c;
pub(crate) const ILOAD_3: u8 = 0x1d;
pub(crate) const LLOAD_0: u8 = 0x1e;
pub(crate) const LLOAD_1: u8 = 0x1f;
pub(crate) const LLOAD_2: u8 = 0x20;
pub(crate) const LLOAD_3: u8 = 0x21;
pub(crate) const FLOAD_0: u8 = 0x22;
pub(crate) const FLOAD_1: u8 = 0x23;
pub(crate) const FLOAD_2: u8 = 0x24;
pub(crate) const FLOAD_3: u8 = 0x25;
pub(crate) const DLOAD_0: u8 = 0x26;
pub(crate) const DLOAD_1: u8 = 0x27;
pub(crate) const DLOAD_2: u8 = 0x28;
pub(crate) const DLOAD_3: u8 = 0x29;
pub(crate) const ISTORE: u8 = 0x36;
pub(crate) const ISTORE_0: u8 = 0x3b;
pub(crate) const ISTORE_1: u8 = 0x3c;
pub(crate) const ISTORE_2: u8 = 0x3d;
pub(crate) const ISTORE_3: u8 = 0x3e;
pub(crate) const TABLESWITCH: u8 = 0xaa;
pub(crate) const LOOKUPSWITCH: u8 = 0xab;
pub(crate) const GOTO: u8 = 0xa7;
pub(crate) const JSR: u8 = 0xa8;
pub(crate) const GOTO_W: u8 = 0xc8;
pub(crate) const JSR_W: u8 = 0xc9;
pub(crate) const IRETURN: u8 = 0xac;
pub(crate) const LRETURN: u8 = 0xad;
pub(crate) const FRETURN: u8 = 0xae;
pub(crate) const DRETURN: u8 = 0xaf;
pub(crate) const ARETURN: u8 = 0xb0;
pub(crate) const RETURN: u8 = 0xb1;
pub(crate) const ARRAYLENGTH: u8 = 0xbe;
pub(crate) const ATHROW: u8 = 0xbf;
pub(crate) const MONITORENTER: u8 = 0xc2;
pub(crate) const MONITOREXIT: u8 = 0xc3;
pub(crate) const ALOAD: u8 = 0x19;
pub(crate) const ALOAD_0: u8 = 0x2a;
pub(crate) const ALOAD_1: u8 = 0x2b;
pub(crate) const ALOAD_2: u8 = 0x2c;
pub(crate) const ALOAD_3: u8 = 0x2d;
pub(crate) const ASTORE: u8 = 0x3a;
pub(crate) const ASTORE_0: u8 = 0x4b;
pub(crate) const ASTORE_1: u8 = 0x4c;
pub(crate) const ASTORE_2: u8 = 0x4d;
pub(crate) const ASTORE_3: u8 = 0x4e;
pub(crate) const POP: u8 = 0x57;
pub(crate) const POP2: u8 = 0x58;
pub(crate) const DUP: u8 = 0x59;
pub(crate) const AASTORE: u8 = 0x53;
pub(crate) const AALOAD: u8 = 0x32;
pub(crate) const IFEQ: u8 = 0x99;
pub(crate) const IFNE: u8 = 0x9a;
pub(crate) const IFLT: u8 = 0x9b;
pub(crate) const IFGE: u8 = 0x9c;
pub(crate) const IFGT: u8 = 0x9d;
pub(crate) const IFLE: u8 = 0x9e;
pub(crate) const IF_ICMPEQ: u8 = 0x9f;
pub(crate) const IF_ICMPNE: u8 = 0xa0;
pub(crate) const IF_ICMPLT: u8 = 0xa1;
pub(crate) const IF_ICMPGE: u8 = 0xa2;
pub(crate) const IF_ICMPGT: u8 = 0xa3;
pub(crate) const IF_ICMPLE: u8 = 0xa4;
pub(crate) const IF_ACMPEQ: u8 = 0xa5;
pub(crate) const IF_ACMPNE: u8 = 0xa6;
pub(crate) const NEW: u8 = 0xbb;
pub(crate) const NEWARRAY: u8 = 0xbc;
pub(crate) const ANEWARRAY: u8 = 0xbd;
pub(crate) const MULTIANEWARRAY: u8 = 0xc5;
pub(crate) const IFNULL: u8 = 0xc6;
pub(crate) const IFNONNULL: u8 = 0xc7;
pub(crate) const INVOKEVIRTUAL: u8 = 0xb6;
pub(crate) const INVOKESPECIAL: u8 = 0xb7;
pub(crate) const INVOKESTATIC: u8 = 0xb8;
pub(crate) const INVOKEINTERFACE: u8 = 0xb9;
pub(crate) const INVOKEDYNAMIC: u8 = 0xba;
pub(crate) const GETSTATIC: u8 = 0xb2;
pub(crate) const PUTSTATIC: u8 = 0xb3;
pub(crate) const GETFIELD: u8 = 0xb4;
pub(crate) const PUTFIELD: u8 = 0xb5;
pub(crate) const IADD: u8 = 0x60;
pub(crate) const LADD: u8 = 0x61;
pub(crate) const FADD: u8 = 0x62;
pub(crate) const DADD: u8 = 0x63;
pub(crate) const ISUB: u8 = 0x64;
pub(crate) const LSUB: u8 = 0x65;
pub(crate) const FSUB: u8 = 0x66;
pub(crate) const DSUB: u8 = 0x67;
pub(crate) const IMUL: u8 = 0x68;
pub(crate) const LMUL: u8 = 0x69;
pub(crate) const FMUL: u8 = 0x6a;
pub(crate) const DMUL: u8 = 0x6b;
pub(crate) const IDIV: u8 = 0x6c;
pub(crate) const LDIV: u8 = 0x6d;
pub(crate) const FDIV: u8 = 0x6e;
pub(crate) const DDIV: u8 = 0x6f;
pub(crate) const IREM: u8 = 0x70;
pub(crate) const LREM: u8 = 0x71;
pub(crate) const FREM: u8 = 0x72;
pub(crate) const DREM: u8 = 0x73;
pub(crate) const ISHL: u8 = 0x78;
pub(crate) const LSHL: u8 = 0x79;
pub(crate) const ISHR: u8 = 0x7a;
pub(crate) const LSHR: u8 = 0x7b;
pub(crate) const IUSHR: u8 = 0x7c;
pub(crate) const LUSHR: u8 = 0x7d;
pub(crate) const IAND: u8 = 0x7e;
pub(crate) const LAND: u8 = 0x7f;
pub(crate) const IOR: u8 = 0x80;
pub(crate) const LOR: u8 = 0x81;
pub(crate) const IXOR: u8 = 0x82;
pub(crate) const LXOR: u8 = 0x83;
pub(crate) const LDC: u8 = 0x12;
pub(crate) const LDC_W: u8 = 0x13;
pub(crate) const LDC2_W: u8 = 0x14;
